chattr_config/__init__.py
chattr_config/config_loader/__init__.py
chattr_config/config_loader/borg.py
chattr_config/config_loader/config/conversion.py
chattr_config/config_loader/config/definitions.py
chattr_config/config_loader/config/loader.py
chattr_config/config_loader/ssm_loader.py
chattr_config/config_loader/yaml_loader.py
chattr_config/decorators/__init__.py
chattr_config/decorators/decorators.py
chattr_config/log_formatter/__init__.py
chattr_config/log_formatter/base_json_log_formatter.py
chattr_config/log_formatter/chattr_json_log_formatter.py
chattr_config/monitoring/__init__.py
chattr_config/monitoring/context.py
chattr_config/monitoring/service/__init__.py
chattr_config/monitoring/service/datadog.py
chattr_config/monitoring/service/mock_monitor.py
chattr_config/monitoring/service/monitor.py
chattr_config/monitoring/service/monitoring_service.py
chattr_config/monitoring/utils.py
chattr_config/utils/__init__.py
chattr_config/utils/system_utils.py
chattr_config-0.1.1.dist-info/WHEEL
chattr_config-0.1.1.dist-info/METADATA
chattr_config-0.1.1.dist-info/RECORD
