Metadata-Version: 2.1
Name: chattr-config
Version: 0.1.1
Summary: 
Author: Chattr
Author-email: chattra23@gmail.com
Requires-Python: >=3.8
Classifier: Programming Language :: Python :: 3
Classifier: Programming Language :: Python :: 3.10
Classifier: Programming Language :: Python :: 3.8
Classifier: Programming Language :: Python :: 3.9
Requires-Dist: PyYAML (>=5.4.1,<6.0.0)
Requires-Dist: boto3 (>=1.9.201)
Requires-Dist: click (>=8.1.3,<8.2.0)
Requires-Dist: dataclasses (>=0.8,<0.9); python_version >= "3.6" and python_version < "3.7"
Requires-Dist: datadog (==0.44.0)
Requires-Dist: ddtrace (>=1.9.2,<2.0.0)
Requires-Dist: pendulum (>=2.1.2,<3.0.0)
Requires-Dist: singleton-decorator (>=1.0.0,<2.0.0)
